excel_transform/__init__.py
excel_transform/gui.py
excel_transform/main_window.py
excel_transform-1.1.5.dist-info/LICENSE
excel_transform-1.1.5.dist-info/METADATA
excel_transform-1.1.5.dist-info/WHEEL
excel_transform-1.1.5.dist-info/entry_points.txt
excel_transform-1.1.5.dist-info/top_level.txt
excel_transform-1.1.5.dist-info/RECORD
