Metadata-Version: 2.1
Name: excel-transform
Version: 1.1.5
Summary: This is a tool to generate an excel file based on a provided source excel and transformation mapping
Home-page: https://github.com/adrian549092/excel_transform
Author: Adrian Martin
Author-email: adrian.m138@gmail.com
License: MIT
Platform: any
Classifier: License :: OSI Approved :: MIT License
Classifier: Programming Language :: Python :: 3.8
Requires-Python: >=3.8
Requires-Dist: click (~=7.1.2)
Requires-Dist: humanfriendly (~=9.1)
Requires-Dist: openpyxl (~=3.0.6)
Requires-Dist: pandas (~=1.2.2)
Requires-Dist: setuptools (~=54.1.2)
Requires-Dist: PyQt5 (~=5.15.2)
